etuCV/__init__.py
etuCV/etuCV.py
etucv-0.0.2.dist-info/licenses/LICENSE
etucv-0.0.2.dist-info/METADATA
etucv-0.0.2.dist-info/WHEEL
etucv-0.0.2.dist-info/top_level.txt
etucv-0.0.2.dist-info/RECORD
