Metadata-Version: 2.4
Name: etuCV
Version: 0.0.2
Summary: A Computer Vision library with high-level functions for educational purposes.
Author-email: Avnish Chitrigi <avnishchitrigi.projects@gmail.com>
Project-URL: Homepage, https://github.com/AvnishChitrigi/etuCV.git
Project-URL: Bug Tracker, https://github.com/AvnishChitrigi/etuCV.git/issues
Classifier: Programming Language :: Python :: 3
Classifier: License :: OSI Approved :: MIT License
Classifier: Operating System :: OS Independent
Classifier: Intended Audience :: Education
Classifier: Topic :: Scientific/Engineering :: Image Processing
Requires-Python: >=3.7
License-File: LICENSE
Requires-Dist: opencv-python-headless
Requires-Dist: numpy
Requires-Dist: matplotlib
Requires-Dist: scikit-image
Dynamic: license-file
